server.py
tools/config.py
tools/v2/federal_accounts.py
tools/v2/recipient.py
tools/v2/spending.py
tools/v2/subawards.py
tools/v2/budget_functions/list_budget_functions.py
tools/v2/financial_spending/major_object_class.py
tools/v2/references/toptier_agencies.py
tools/v2/references/total_budgetary_resources.py
tools/v2/search/config.py
tools/v2/search/spending_by_award.py
tools/v2/search/spending_over_time.py
utils/http.py
usaspending_mcp_server-0.1.2.dist-info/METADATA
usaspending_mcp_server-0.1.2.dist-info/WHEEL
usaspending_mcp_server-0.1.2.dist-info/entry_points.txt
usaspending_mcp_server-0.1.2.dist-info/licenses/LICENSE
usaspending_mcp_server-0.1.2.dist-info/RECORD
