Metadata-Version: 2.4
Name: usaspending-mcp-server
Version: 0.1.2
Summary: This is an MCP server to interact with the USASPENDING.gov API
Project-URL: Repository, https://github.com/thsmale/usaspending-mcp-server
Author-email: Thomas Smale <tom.snail.mail@gmail.com>
License-Expression: MIT
License-File: LICENSE
Requires-Python: >=3.10
Requires-Dist: anyio>=4.11.0
Requires-Dist: dotenv>=0.9.9
Requires-Dist: httpx>=0.28.1
Requires-Dist: jsonschema>=4.25.1
Requires-Dist: mcp>=1.16.0
Requires-Dist: starlette>=0.48.0
Requires-Dist: uvicorn>=0.37.0
